sqoopit/MapredJob.py
sqoopit/SqoopImport.py
sqoopit/SqoopJob.py
sqoopit/__init__.py
unittests/__init__.py
unittests/unintary_tests.py
sqoopit-0.0.12.dist-info/LICENSE
sqoopit-0.0.12.dist-info/METADATA
sqoopit-0.0.12.dist-info/WHEEL
sqoopit-0.0.12.dist-info/top_level.txt
sqoopit-0.0.12.dist-info/RECORD
