Metadata-Version: 2.1
Name: sqoopit
Version: 0.0.12
Summary: A simple package to let you Sqoop into HDFS/Hive/HBase with python
Home-page: https://github.com/marco-gallegos/sqoopit
Author: Marco A. Gallegos
Author-email: ma_galeza@hotmail.com
License: UNKNOWN
Platform: UNKNOWN
Classifier: Programming Language :: Python :: 3
Classifier: License :: OSI Approved :: MIT License
Classifier: Operating System :: OS Independent
